setup.cfg
setup.py
GoogleTensor/__init__.py
GoogleTensor/engine.py
GoogleTensor.egg-info/PKG-INFO
GoogleTensor.egg-info/SOURCES.txt
GoogleTensor.egg-info/dependency_links.txt
GoogleTensor.egg-info/not-zip-safe
GoogleTensor.egg-info/top_level.txt