Metadata-Version: 1.0
Name: GoogleTensor
Version: 2.0
Summary: Tensor can throttle.
Home-page: UNKNOWN
Author: UNKNOWN
Author-email: aleksandrparnuk7@gmail.com
License: UNKNOWN
Platform: UNKNOWN
